acquire_movie_data/__init__.py
acquire_movie_data/get_movie_data.py
acquire_movie_data-0.1.4.dist-info/METADATA
acquire_movie_data-0.1.4.dist-info/WHEEL
acquire_movie_data-0.1.4.dist-info/RECORD
