Metadata-Version: 2.1
Name: acquire_movie_data
Version: 0.1.4
Summary: 
Author: zhanghuihui111
Author-email: 2019110851@stu.sufe.edu.cn
Requires-Python: >=3.12,<4.0
Classifier: Programming Language :: Python :: 3
Classifier: Programming Language :: Python :: 3.12
Requires-Dist: beautifulsoup4 (>=4.12.3,<5.0.0)
Requires-Dist: requests (>=2.32.3,<3.0.0)
